keplemon/.DS_Store
keplemon/EGM-2008.GEO
keplemon/EGM-96.GEO
keplemon/JPLcon_1950_2050.405
keplemon/SGP4_Open_License.txt
keplemon/WGS84-70.GEO
keplemon/__init__.py
keplemon/__init__.pyi
keplemon/__main__.py
keplemon/_keplemon.abi3.so
keplemon/bodies.py
keplemon/bodies.pyi
keplemon/catalogs.py
keplemon/catalogs.pyi
keplemon/elements.py
keplemon/elements.pyi
keplemon/enums.py
keplemon/enums.pyi
keplemon/estimation.py
keplemon/estimation.pyi
keplemon/events.py
keplemon/events.pyi
keplemon/exceptions.py
keplemon/libastrofunc.dylib
keplemon/libdllmain.dylib
keplemon/libelops.dylib
keplemon/libenvconst.dylib
keplemon/libextephem.dylib
keplemon/libgcc_s.1.1.dylib
keplemon/libgfortran.5.dylib
keplemon/libgomp.1.dylib
keplemon/libobs.dylib
keplemon/libquadmath.0.dylib
keplemon/libsatstate.dylib
keplemon/libsensor.dylib
keplemon/libsgp4prop.dylib
keplemon/libspvec.dylib
keplemon/libtimefunc.dylib
keplemon/libtle.dylib
keplemon/libvcm.dylib
keplemon/propagation.py
keplemon/propagation.pyi
keplemon/py.typed
keplemon/time.py
keplemon/time.pyi
keplemon/time_constants.dat
keplemon-3.6.2.dist-info/METADATA
keplemon-3.6.2.dist-info/WHEEL
keplemon-3.6.2.dist-info/entry_points.txt
keplemon-3.6.2.dist-info/RECORD
