Metadata-Version: 2.4
Name: keplemon
Version: 3.6.2
Requires-Dist: requests
Requires-Dist: click
Requires-Dist: maturin>=1.0,<2.0 ; extra == 'dev'
Requires-Dist: keplemon[test] ; extra == 'dev'
Requires-Dist: mkdocstrings[python] ; extra == 'dev'
Requires-Dist: mkdocs-material ; extra == 'dev'
Requires-Dist: markdown-include ; extra == 'dev'
Requires-Dist: tomli ; python_full_version < '3.11' and extra == 'dev'
Requires-Dist: pytest ; extra == 'test'
Provides-Extra: dev
Provides-Extra: test
Summary: Citra Space Corporation's Rust-accelerated astrodynamics library.
Author-email: Brandon Sexton <brandon@citra.space>
License-Expression: MIT
Requires-Python: >=3.9
Project-URL: Documentation, https://keplemon.citra.space
Project-URL: Issues, https://github.com/citra-space/keplemon/issues
Project-URL: Repository, https://github.com/citra-space/keplemon.git
